pl_sugar/__init__.py
pl_sugar/models.py
pl_sugar/utils.py
pl_sugar/validators.py
pl_sugar/rest_framework/__init__.py
pl_sugar/rest_framework/pagination.py
pl_sugar/social_auth/__init__.py
pl_sugar/social_auth/pipeline.py
pl_sugar/templates/admin/filter.html
pl_sugar/templates/admin/login.html
presslabs_sugar-1.2.0.dist-info/DESCRIPTION.rst
presslabs_sugar-1.2.0.dist-info/METADATA
presslabs_sugar-1.2.0.dist-info/RECORD
presslabs_sugar-1.2.0.dist-info/WHEEL
presslabs_sugar-1.2.0.dist-info/metadata.json
presslabs_sugar-1.2.0.dist-info/top_level.txt
