Metadata-Version: 2.0
Name: presslabs-sugar
Version: 1.2.0
Summary: Various sugars and goodies for projects.
Home-page: https://github.com/PressLabs/sugar
Author: Presslabs SRL
Author-email: ping@presslabs.com
License: MIT
Platform: UNKNOWN
Classifier: Environment :: Web Environment
Classifier: Framework :: Django
Classifier: Intended Audience :: Developers
Classifier: Operating System :: OS Independent
Classifier: Programming Language :: Python
Classifier: Programming Language :: Python :: 2.7
Classifier: Programming Language :: Python :: 3
Classifier: Programming Language :: Python :: 3.5
Provides-Extra: test
Requires-Dist: pytest; extra == 'test'
Requires-Dist: pytest-flake8; extra == 'test'
Requires-Dist: pytest-runner (>=2.0,<3dev); extra == 'test'
